Tools/Verilog/ANcodesDecoder/files/Uni_HL_20221007_1058/ANdecoder_Uni_HL_29_for_N_23234.v
// File Name: ./files/Uni_HL_20221007_1058/ANdecoder_Uni_HL_29_for_N_23234.v
// module= 29
// 可更正AN的bit數= 28
// mod的bit數= 5
// 可更正N的bit數= 23

module ANdecoder(ANe, Nc);
input [27:0] ANe;
output [22:0] Nc;
wire [4:0] mod_tri;
wire [4:0] not_mod_tri;
wire [27:0] error_bit;
wire [27:0] ANc;
assign mod_tri = ANe % 29;

//not gate
not not_0(not_mod_tri[0], mod_tri[0]);
not not_1(not_mod_tri[1], mod_tri[1]);
not not_2(not_mod_tri[2], mod_tri[2]);
not not_3(not_mod_tri[3], mod_tri[3]);
not not_4(not_mod_tri[4], mod_tri[4]);
//and gate
and and_1(error_bit[14], mod_tri[0], not_mod_tri[1], not_mod_tri[2], not_mod_tri[3], not_mod_tri[4]);
and and_2(error_bit[15], not_mod_tri[0], mod_tri[1], not_mod_tri[2], not_mod_tri[3], not_mod_tri[4]);
and and_3(error_bit[19], mod_tri[0], mod_tri[1], not_mod_tri[2], not_mod_tri[3], not_mod_tri[4]);
and and_4(error_bit[16], not_mod_tri[0], not_mod_tri[1], mod_tri[2], not_mod_tri[3], not_mod_tri[4]);
and and_5(error_bit[8], mod_tri[0], not_mod_tri[1], mod_tri[2], not_mod_tri[3], not_mod_tri[4]);
and and_6(error_bit[20], not_mod_tri[0], mod_tri[1], mod_tri[2], not_mod_tri[3], not_mod_tri[4]);
and and_7(error_bit[26], mod_tri[0], mod_tri[1], mod_tri[2], not_mod_tri[3], not_mod_tri[4]);
and and_8(error_bit[17], not_mod_tri[0], not_mod_tri[1], not_mod_tri[2], mod_tri[3], not_mod_tri[4]);
and and_9(error_bit[24], mod_tri[0], not_mod_tri[1], not_mod_tri[2], mod_tri[3], not_mod_tri[4]);
and and_10(error_bit[9], not_mod_tri[0], mod_tri[1], not_mod_tri[2], mod_tri[3], not_mod_tri[4]);
and and_11(error_bit[11], mod_tri[0], mod_tri[1], not_mod_tri[2], mod_tri[3], not_mod_tri[4]);
and and_12(error_bit[21], not_mod_tri[0], not_mod_tri[1], mod_tri[2], mod_tri[3], not_mod_tri[4]);
and and_13(error_bit[4], mod_tri[0], not_mod_tri[1], mod_tri[2], mod_tri[3], not_mod_tri[4]);
and and_14(error_bit[27], not_mod_tri[0], mod_tri[1], mod_tri[2], mod_tri[3], not_mod_tri[4]);
and and_15(error_bit[13], mod_tri[0], mod_tri[1], mod_tri[2], mod_tri[3], not_mod_tri[4]);
and and_16(error_bit[18], not_mod_tri[0], not_mod_tri[1], not_mod_tri[2], not_mod_tri[3], mod_tri[4]);
and and_17(error_bit[7], mod_tri[0], not_mod_tri[1], not_mod_tri[2], not_mod_tri[3], mod_tri[4]);
and and_18(error_bit[25], not_mod_tri[0], mod_tri[1], not_mod_tri[2], not_mod_tri[3], mod_tri[4]);
and and_19(error_bit[23], mod_tri[0], mod_tri[1], not_mod_tri[2], not_mod_tri[3], mod_tri[4]);
and and_20(error_bit[10], not_mod_tri[0], not_mod_tri[1], mod_tri[2], not_mod_tri[3], mod_tri[4]);
and and_21(error_bit[3], mod_tri[0], not_mod_tri[1], mod_tri[2], not_mod_tri[3], mod_tri[4]);
and and_22(error_bit[12], not_mod_tri[0], mod_tri[1], mod_tri[2], not_mod_tri[3], mod_tri[4]);
and and_23(error_bit[6], mod_tri[0], mod_tri[1], mod_tri[2], not_mod_tri[3], mod_tri[4]);
and and_24(error_bit[22], not_mod_tri[0], not_mod_tri[1], not_mod_tri[2], mod_tri[3], mod_tri[4]);
and and_25(error_bit[2], mod_tri[0], not_mod_tri[1], not_mod_tri[2], mod_tri[3], mod_tri[4]);
and and_26(error_bit[5], not_mod_tri[0], mod_tri[1], not_mod_tri[2], mod_tri[3], mod_tri[4]);
and and_27(error_bit[1], mod_tri[0], mod_tri[1], not_mod_tri[2], mod_tri[3], mod_tri[4]);
and and_28(error_bit[0], not_mod_tri[0], not_mod_tri[1], mod_tri[2], mod_tri[3], mod_tri[4]);
//or gate
or or_0(ANc[0],error_bit[0], ANe[0]);
or or_1(ANc[1],error_bit[1], ANe[1]);
or or_2(ANc[2],error_bit[2], ANe[2]);
or or_3(ANc[3],error_bit[3], ANe[3]);
or or_4(ANc[4],error_bit[4], ANe[4]);
or or_5(ANc[5],error_bit[5], ANe[5]);
or or_6(ANc[6],error_bit[6], ANe[6]);
or or_7(ANc[7],error_bit[7], ANe[7]);
or or_8(ANc[8],error_bit[8], ANe[8]);
or or_9(ANc[9],error_bit[9], ANe[9]);
or or_10(ANc[10],error_bit[10], ANe[10]);
or or_11(ANc[11],error_bit[11], ANe[11]);
or or_12(ANc[12],error_bit[12], ANe[12]);
or or_13(ANc[13],error_bit[13], ANe[13]);
or or_14(ANc[14],error_bit[14], ANe[14]);
or or_15(ANc[15],error_bit[15], ANe[15]);
or or_16(ANc[16],error_bit[16], ANe[16]);
or or_17(ANc[17],error_bit[17], ANe[17]);
or or_18(ANc[18],error_bit[18], ANe[18]);
or or_19(ANc[19],error_bit[19], ANe[19]);
or or_20(ANc[20],error_bit[20], ANe[20]);
or or_21(ANc[21],error_bit[21], ANe[21]);
or or_22(ANc[22],error_bit[22], ANe[22]);
or or_23(ANc[23],error_bit[23], ANe[23]);
or or_24(ANc[24],error_bit[24], ANe[24]);
or or_25(ANc[25],error_bit[25], ANe[25]);
or or_26(ANc[26],error_bit[26], ANe[26]);
or or_27(ANc[27],error_bit[27], ANe[27]);
assign Nc = ANc / 29;

endmodule

Tools/Verilog/ANcodesDecoder/files/Uni_HL_20221007_1058/ANdecoder_Uni_HL_29_tb_for_N_23234.v
// File Name: ./files/Uni_HL_20221007_1058/ANdecoder_Uni_HL_29_tb_for_N_23234.v
// module= 29
// N= 23234

module ANdecoder_tb;
reg [27:0] ANe;
wire [22:0] Nc;

ANdecoder D0(ANe, Nc);
initial begin
$dumpfile("./files/Uni_HL_20221007_1058/A29N23234.vcd"); 
$dumpvars(0, ANdecoder_tb);

ANe=28'd0;

ANe=28'd673784; //R=27, error bit=1
#10 ANe=28'd673778; //R=21, error bit=3
#10 ANe=28'd673770; //R=13, error bit=4
#10 ANe=28'd673754; //R=26, error bit=5
#10 ANe=28'd673722; //R=23, error bit=6
#10 ANe=28'd673658; //R=17, error bit=7
#10 ANe=28'd673530; //R=5, error bit=8
#10 ANe=28'd673274; //R=10, error bit=9
#10 ANe=28'd672762; //R=20, error bit=10
#10 ANe=28'd657402; //R=1, error bit=14
#10 ANe=28'd542714; //R=8, error bit=17
#10 ANe=28'd149498; //R=3, error bit=19
#10 $finish;
end
endmodule

Tools/Verilog/ANcodesDecoder/files/Uni_HL_20221007_1058/A29N23234.vcd
$date
	Fri Oct 07 10:58:01 2022
$end
$version
	Icarus Verilog
$end
$timescale
	1s
$end
$scope module ANdecoder_tb $end
$var wire 23 ! Nc [22:0] $end
$var reg 28 " ANe [27:0] $end
$scope module D0 $end
$var wire 28 # ANe [27:0] $end
$var wire 5 $ not_mod_tri [4:0] $end
$var wire 5 % mod_tri [4:0] $end
$var wire 28 & error_bit [27:0] $end
$var wire 23 ' Nc [22:0] $end
$var wire 28 ( ANc [27:0] $end
$upscope $end
$upscope $end
$enddefinitions $end
#0
$dumpvars
b10100100011111111010 (
b101101011000010 '
b10 &
b11011 %
b100 $
b10100100011111111000 #
b10100100011111111000 "
b101101011000010 !
$end
#10
b1000 &
b1010 $
b101101011000010 !
b101101011000010 '
b10100100011111111010 (
b10101 %
b10100100011111110010 "
b10100100011111110010 #
#20
b10000 &
b10010 $
b101101011000010 !
b101101011000010 '
b10100100011111111010 (
b1101 %
b10100100011111101010 "
b10100100011111101010 #
#30
b100000 &
b101 $
b101101011000010 !
b101101011000010 '
b10100100011111111010 (
b11010 %
b10100100011111011010 "
b10100100011111011010 #
#40
b1000000 &
b1000 $
b101101011000010 !
b101101011000010 '
b10100100011111111010 (
b10111 %
b10100100011110111010 "
b10100100011110111010 #
#50
b10000000 &
b1110 $
b101101011000010 !
b101101011000010 '
b10100100011111111010 (
b10001 %
b10100100011101111010 "
b10100100011101111010 #
#60
b100000000 &
b11010 $
b101101011000010 !
b101101011000010 '
b10100100011111111010 (
b101 %
b10100100011011111010 "
b10100100011011111010 #
#70
b1000000000 &
b10101 $
b101101011000010 !
b101101011000010 '
b10100100011111111010 (
b1010 %
b10100100010111111010 "
b10100100010111111010 #
#80
b10000000000 &
b1011 $
b101101011000010 !
b101101011000010 '
b10100100011111111010 (
b10100 %
b10100100001111111010 "
b10100100001111111010 #
#90
b100000000000000 &
b11110 $
b101101011000010 !
b101101011000010 '
b10100100011111111010 (
b1 %
b10100000011111111010 "
b10100000011111111010 #
#100
b100000000000000000 &
b10111 $
b101101011000010 !
b101101011000010 '
b10100100011111111010 (
b1000 %
b10000100011111111010 "
b10000100011111111010 #
#110
b10000000000000000000 &
b11100 $
b101101011000010 !
b101101011000010 '
b10100100011111111010 (
b11 %
b100100011111111010 "
b100100011111111010 #
