Tools/Verilog/ANcodesDecoder/files/BER_20221006_1611/ANdecoder_BER_19_for_N_11.v
// File Name: ./files/BER_20221006_1611/ANdecoder_BER_19_for_N_11.v
// module= 19
// 可更正AN的bit數= 9
// mod的bit數= 5
// 可更正N的bit數= 4

module ANdecoder(ANe, Nc);
input [8:0] ANe;
output [3:0] Nc;
wire [4:0] mod_tri;
wire [4:0] not_mod_tri;
wire [8:0] error_bit;
wire [17:0] and_out;
wire [8:0] ANc;

assign mod_tri = ANe % 19;

//not gate
not not_0(not_mod_tri[0], mod_tri[0]);
not not_1(not_mod_tri[1], mod_tri[1]);
not not_2(not_mod_tri[2], mod_tri[2]);
not not_3(not_mod_tri[3], mod_tri[3]);
not not_4(not_mod_tri[4], mod_tri[4]);
//and gate
and and_1(and_out[0], mod_tri[0], not_mod_tri[1], not_mod_tri[2], not_mod_tri[3], not_mod_tri[4]);
and and_2(and_out[1], not_mod_tri[0], mod_tri[1], not_mod_tri[2], not_mod_tri[3], not_mod_tri[4]);
and and_3(and_out[2], mod_tri[0], mod_tri[1], not_mod_tri[2], not_mod_tri[3], not_mod_tri[4]);
and and_4(and_out[3], not_mod_tri[0], not_mod_tri[1], mod_tri[2], not_mod_tri[3], not_mod_tri[4]);
and and_5(and_out[4], mod_tri[0], not_mod_tri[1], mod_tri[2], not_mod_tri[3], not_mod_tri[4]);
and and_6(and_out[5], not_mod_tri[0], mod_tri[1], mod_tri[2], not_mod_tri[3], not_mod_tri[4]);
and and_7(and_out[6], mod_tri[0], mod_tri[1], mod_tri[2], not_mod_tri[3], not_mod_tri[4]);
and and_8(and_out[7], not_mod_tri[0], not_mod_tri[1], not_mod_tri[2], mod_tri[3], not_mod_tri[4]);
and and_9(and_out[8], mod_tri[0], not_mod_tri[1], not_mod_tri[2], mod_tri[3], not_mod_tri[4]);
and and_10(and_out[9], not_mod_tri[0], mod_tri[1], not_mod_tri[2], mod_tri[3], not_mod_tri[4]);
and and_11(and_out[10], mod_tri[0], mod_tri[1], not_mod_tri[2], mod_tri[3], not_mod_tri[4]);
and and_12(and_out[11], not_mod_tri[0], not_mod_tri[1], mod_tri[2], mod_tri[3], not_mod_tri[4]);
and and_13(and_out[12], mod_tri[0], not_mod_tri[1], mod_tri[2], mod_tri[3], not_mod_tri[4]);
and and_14(and_out[13], not_mod_tri[0], mod_tri[1], mod_tri[2], mod_tri[3], not_mod_tri[4]);
and and_15(and_out[14], mod_tri[0], mod_tri[1], mod_tri[2], mod_tri[3], not_mod_tri[4]);
and and_16(and_out[15], not_mod_tri[0], not_mod_tri[1], not_mod_tri[2], not_mod_tri[3], mod_tri[4]);
and and_17(and_out[16], mod_tri[0], not_mod_tri[1], not_mod_tri[2], not_mod_tri[3], mod_tri[4]);
and and_18(and_out[17], not_mod_tri[0], mod_tri[1], not_mod_tri[2], not_mod_tri[3], mod_tri[4]);
//or gate
or or_0(error_bit[0], and_out[0], and_out[17]);
or or_1(error_bit[1], and_out[1], and_out[16]);
or or_2(error_bit[2], and_out[3], and_out[14]);
or or_3(error_bit[3], and_out[7], and_out[10]);
or or_4(error_bit[4], and_out[2], and_out[15]);
or or_5(error_bit[5], and_out[5], and_out[12]);
or or_6(error_bit[6], and_out[6], and_out[11]);
or or_7(error_bit[7], and_out[4], and_out[13]);
or or_8(error_bit[8], and_out[8], and_out[9]);
//xor gate
xor xor_0(ANc[0],error_bit[0],ANe[0]);
xor xor_1(ANc[1],error_bit[1],ANe[1]);
xor xor_2(ANc[2],error_bit[2],ANe[2]);
xor xor_3(ANc[3],error_bit[3],ANe[3]);
xor xor_4(ANc[4],error_bit[4],ANe[4]);
xor xor_5(ANc[5],error_bit[5],ANe[5]);
xor xor_6(ANc[6],error_bit[6],ANe[6]);
xor xor_7(ANc[7],error_bit[7],ANe[7]);
xor xor_8(ANc[8],error_bit[8],ANe[8]);
assign Nc = ANc / 19;

endmodule

Tools/Verilog/ANcodesDecoder/files/BER_20221006_1611/ANdecoder_BER_19_tb_for_N_11.v
// File Name: ./files/BER_20221006_1611/ANdecoder_BER_19_tb_for_N_11.v
// module= 19
// N= 11

module ANdecoder_tb;
reg [8:0] ANe;
wire [3:0] Nc;

ANdecoder D0(ANe, Nc);
initial begin
$dumpfile("./files/BER_20221006_1611/A19N11.vcd"); 
$dumpvars(0, ANdecoder_tb);

ANe=9'd211; //R=2, error bit=1
#10 ANe=9'd213; //R=4, error bit=2
#10 ANe=9'd217; //R=8, error bit=3
#10 ANe=9'd241; //R=13, error bit=5
#10 ANe=9'd465; //R=9, error bit=8
#10 ANe=9'd208; //R=18, error bit=0
#10 ANe=9'd193; //R=3, error bit=4
#10 ANe=9'd145; //R=12, error bit=6
#10 ANe=9'd81; //R=5, error bit=7
#10 $finish;
end
endmodule

Tools/Verilog/ANcodesDecoder/files/BER_20221006_1611/A19N11.vcd
$date
	Thu Oct 06 16:11:41 2022
$end
$version
	Icarus Verilog
$end
$timescale
	1s
$end
$scope module ANdecoder_tb $end
$var wire 4 ! Nc [3:0] $end
$var reg 9 " ANe [8:0] $end
$scope module D0 $end
$var wire 9 # ANe [8:0] $end
$var wire 5 $ not_mod_tri [4:0] $end
$var wire 5 % mod_tri [4:0] $end
$var wire 9 & error_bit [8:0] $end
$var wire 18 ' and_out [17:0] $end
$var wire 4 ( Nc [3:0] $end
$var wire 9 ) ANc [8:0] $end
$upscope $end
$upscope $end
$enddefinitions $end
#0
$dumpvars
b11010001 )
b1011 (
b10 '
b10 &
b10 %
b11101 $
b11010011 #
b11010011 "
b1011 !
$end
#10
b100 &
b1000 '
b11011 $
b11010001 )
b100 %
b11010101 "
b11010101 #
#20
b1000 &
b10000000 '
b10111 $
b11010001 )
b1000 %
b11011001 "
b11011001 #
#30
b100000 &
b1000000000000 '
b10010 $
b1011 !
b1011 (
b11010001 )
b1101 %
b11110001 "
b11110001 #
#40
b100000000 &
b100000000 '
b10110 $
b1011 !
b1011 (
b11010001 )
b1001 %
b111010001 "
b111010001 #
#50
b1 &
b100000000000000000 '
b1101 $
b1011 !
b1011 (
b11010001 )
b10010 %
b11010000 "
b11010000 #
#60
b10000 &
b100 '
b11100 $
b1011 !
b1011 (
b11010001 )
b11 %
b11000001 "
b11000001 #
#70
b1000000 &
b100000000000 '
b10011 $
b1011 !
b1011 (
b11010001 )
b1100 %
b10010001 "
b10010001 #
#80
b10000000 &
b10000 '
b11010 $
b1011 !
b1011 (
b11010001 )
b101 %
b1010001 "
b1010001 #
