Tools/Verilog/ANcodesDecoder/files/Alter_20221007_1058/ANdecoder_Alter_29_for_N_1312.v
// File Name: ./files/Alter_20221007_1058/ANdecoder_Alter_29_for_N_1312.v
// module= 29
// 可更正AN的bit數= 28
// mod的bit數= 5
// 可更正N的bit數= 23

module ANdecoder(ANe, Nc);
input [27:0] ANe;
output [22:0] Nc;
wire [4:0] mod_tri;
wire [4:0] not_mod_tri;
wire [27:0] R;
wire [27:0] notR;
wire [27:0] ANc1;
wire [27:0] ANc2;
wire [4:0] check;
wire [27:0] ANc;

assign mod_tri = ANe % 29;

//not0 gate
not not0_0(not_mod_tri[0], mod_tri[0]);
not not0_1(not_mod_tri[1], mod_tri[1]);
not not0_2(not_mod_tri[2], mod_tri[2]);
not not0_3(not_mod_tri[3], mod_tri[3]);
not not0_4(not_mod_tri[4], mod_tri[4]);
//and gate
and and0_1(R[0], mod_tri[0], not_mod_tri[1], not_mod_tri[2], not_mod_tri[3], not_mod_tri[4]);
and and0_2(R[1], not_mod_tri[0], mod_tri[1], not_mod_tri[2], not_mod_tri[3], not_mod_tri[4]);
and and0_3(R[2], mod_tri[0], mod_tri[1], not_mod_tri[2], not_mod_tri[3], not_mod_tri[4]);
and and0_4(R[3], not_mod_tri[0], not_mod_tri[1], mod_tri[2], not_mod_tri[3], not_mod_tri[4]);
and and0_5(R[4], mod_tri[0], not_mod_tri[1], mod_tri[2], not_mod_tri[3], not_mod_tri[4]);
and and0_6(R[5], not_mod_tri[0], mod_tri[1], mod_tri[2], not_mod_tri[3], not_mod_tri[4]);
and and0_7(R[6], mod_tri[0], mod_tri[1], mod_tri[2], not_mod_tri[3], not_mod_tri[4]);
and and0_8(R[7], not_mod_tri[0], not_mod_tri[1], not_mod_tri[2], mod_tri[3], not_mod_tri[4]);
and and0_9(R[8], mod_tri[0], not_mod_tri[1], not_mod_tri[2], mod_tri[3], not_mod_tri[4]);
and and0_10(R[9], not_mod_tri[0], mod_tri[1], not_mod_tri[2], mod_tri[3], not_mod_tri[4]);
and and0_11(R[10], mod_tri[0], mod_tri[1], not_mod_tri[2], mod_tri[3], not_mod_tri[4]);
and and0_12(R[11], not_mod_tri[0], not_mod_tri[1], mod_tri[2], mod_tri[3], not_mod_tri[4]);
and and0_13(R[12], mod_tri[0], not_mod_tri[1], mod_tri[2], mod_tri[3], not_mod_tri[4]);
and and0_14(R[13], not_mod_tri[0], mod_tri[1], mod_tri[2], mod_tri[3], not_mod_tri[4]);
and and0_15(R[14], mod_tri[0], mod_tri[1], mod_tri[2], mod_tri[3], not_mod_tri[4]);
and and0_16(R[15], not_mod_tri[0], not_mod_tri[1], not_mod_tri[2], not_mod_tri[3], mod_tri[4]);
and and0_17(R[16], mod_tri[0], not_mod_tri[1], not_mod_tri[2], not_mod_tri[3], mod_tri[4]);
and and0_18(R[17], not_mod_tri[0], mod_tri[1], not_mod_tri[2], not_mod_tri[3], mod_tri[4]);
and and0_19(R[18], mod_tri[0], mod_tri[1], not_mod_tri[2], not_mod_tri[3], mod_tri[4]);
and and0_20(R[19], not_mod_tri[0], not_mod_tri[1], mod_tri[2], not_mod_tri[3], mod_tri[4]);
and and0_21(R[20], mod_tri[0], not_mod_tri[1], mod_tri[2], not_mod_tri[3], mod_tri[4]);
and and0_22(R[21], not_mod_tri[0], mod_tri[1], mod_tri[2], not_mod_tri[3], mod_tri[4]);
and and0_23(R[22], mod_tri[0], mod_tri[1], mod_tri[2], not_mod_tri[3], mod_tri[4]);
and and0_24(R[23], not_mod_tri[0], not_mod_tri[1], not_mod_tri[2], mod_tri[3], mod_tri[4]);
and and0_25(R[24], mod_tri[0], not_mod_tri[1], not_mod_tri[2], mod_tri[3], mod_tri[4]);
and and0_26(R[25], not_mod_tri[0], mod_tri[1], not_mod_tri[2], mod_tri[3], mod_tri[4]);
and and0_27(R[26], mod_tri[0], mod_tri[1], not_mod_tri[2], mod_tri[3], mod_tri[4]);
and and0_28(R[27], not_mod_tri[0], not_mod_tri[1], mod_tri[2], mod_tri[3], mod_tri[4]);
//not1 gate
not not1_0(notR[0], R[0]);
not not1_1(notR[1], R[1]);
not not1_2(notR[2], R[2]);
not not1_3(notR[3], R[3]);
not not1_4(notR[4], R[4]);
not not1_5(notR[5], R[5]);
not not1_6(notR[6], R[6]);
not not1_7(notR[7], R[7]);
not not1_8(notR[8], R[8]);
not not1_9(notR[9], R[9]);
not not1_10(notR[10], R[10]);
not not1_11(notR[11], R[11]);
not not1_12(notR[12], R[12]);
not not1_13(notR[13], R[13]);
not not1_14(notR[14], R[14]);
not not1_15(notR[15], R[15]);
not not1_16(notR[16], R[16]);
not not1_17(notR[17], R[17]);
not not1_18(notR[18], R[18]);
not not1_19(notR[19], R[19]);
not not1_20(notR[20], R[20]);
not not1_21(notR[21], R[21]);
not not1_22(notR[22], R[22]);
not not1_23(notR[23], R[23]);
not not1_24(notR[24], R[24]);
not not1_25(notR[25], R[25]);
not not1_26(notR[26], R[26]);
not not1_27(notR[27], R[27]);
//and1 gate
and and1_0(ANc1[0], notR[0], ANe[0]);
and and1_1(ANc1[1], notR[1], ANe[1]);
and and1_5(ANc1[5], notR[2], ANe[5]);
and and1_2(ANc1[2], notR[3], ANe[2]);
and and1_22(ANc1[22], notR[4], ANe[22]);
and and1_6(ANc1[6], notR[5], ANe[6]);
and and1_12(ANc1[12], notR[6], ANe[12]);
and and1_3(ANc1[3], notR[7], ANe[3]);
and and1_10(ANc1[10], notR[8], ANe[10]);
and and1_23(ANc1[23], notR[9], ANe[23]);
and and1_25(ANc1[25], notR[10], ANe[25]);
and and1_7(ANc1[7], notR[11], ANe[7]);
and and1_18(ANc1[18], notR[12], ANe[18]);
and and1_13(ANc1[13], notR[13], ANe[13]);
and and1_27(ANc1[27], notR[14], ANe[27]);
and and1_4(ANc1[4], notR[15], ANe[4]);
and and1_21(ANc1[21], notR[16], ANe[21]);
and and1_11(ANc1[11], notR[17], ANe[11]);
and and1_9(ANc1[9], notR[18], ANe[9]);
and and1_24(ANc1[24], notR[19], ANe[24]);
and and1_17(ANc1[17], notR[20], ANe[17]);
and and1_26(ANc1[26], notR[21], ANe[26]);
and and1_20(ANc1[20], notR[22], ANe[20]);
and and1_8(ANc1[8], notR[23], ANe[8]);
and and1_16(ANc1[16], notR[24], ANe[16]);
and and1_19(ANc1[19], notR[25], ANe[19]);
and and1_15(ANc1[15], notR[26], ANe[15]);
and and1_14(ANc1[14], notR[27], ANe[14]);
//or gate
or or_14(ANc2[14], R[0], ANe[14]);
or or_15(ANc2[15], R[1], ANe[15]);
or or_19(ANc2[19], R[2], ANe[19]);
or or_16(ANc2[16], R[3], ANe[16]);
or or_8(ANc2[8], R[4], ANe[8]);
or or_20(ANc2[20], R[5], ANe[20]);
or or_26(ANc2[26], R[6], ANe[26]);
or or_17(ANc2[17], R[7], ANe[17]);
or or_24(ANc2[24], R[8], ANe[24]);
or or_9(ANc2[9], R[9], ANe[9]);
or or_11(ANc2[11], R[10], ANe[11]);
or or_21(ANc2[21], R[11], ANe[21]);
or or_4(ANc2[4], R[12], ANe[4]);
or or_27(ANc2[27], R[13], ANe[27]);
or or_13(ANc2[13], R[14], ANe[13]);
or or_18(ANc2[18], R[15], ANe[18]);
or or_7(ANc2[7], R[16], ANe[7]);
or or_25(ANc2[25], R[17], ANe[25]);
or or_23(ANc2[23], R[18], ANe[23]);
or or_10(ANc2[10], R[19], ANe[10]);
or or_3(ANc2[3], R[20], ANe[3]);
or or_12(ANc2[12], R[21], ANe[12]);
or or_6(ANc2[6], R[22], ANe[6]);
or or_22(ANc2[22], R[23], ANe[22]);
or or_2(ANc2[2], R[24], ANe[2]);
or or_5(ANc2[5], R[25], ANe[5]);
or or_1(ANc2[1], R[26], ANe[1]);
or or_0(ANc2[0], R[27], ANe[0]);
//check
assign check = ANc1 % 29;
assign ANc = (check == 5'd0) ? ANc1 : ANc2;
assign Nc = ANc / 29;
endmodule

Tools/Verilog/ANcodesDecoder/files/Alter_20221007_1058/ANdecoder_Alter_29_tb_for_N_1312.v
// File Name: ./files/Alter_20221007_1058/ANdecoder_Alter_29_tb_for_N_1312.v
// module= 29
// N= 1312

module ANdecoder_tb;
reg [27:0] ANe;
wire [22:0] Nc;

ANdecoder D0(ANe, Nc);
initial begin
$dumpfile("./files/Alter_20221007_1058/A29N1312.vcd"); 
$dumpvars(0, ANdecoder_tb);

ANe=28'd38049; //R=1, error bit=0
#10 ANe=28'd38050; //R=2, error bit=1
#10 ANe=28'd38052; //R=4, error bit=2
#10 ANe=28'd38056; //R=8, error bit=3
#10 ANe=28'd38064; //R=16, error bit=4
#10 ANe=28'd38112; //R=6, error bit=6
#10 ANe=28'd38304; //R=24, error bit=8
#10 ANe=28'd38560; //R=19, error bit=9
#10 ANe=28'd40096; //R=18, error bit=11
#10 ANe=28'd46240; //R=14, error bit=13
#10 ANe=28'd54432; //R=28, error bit=14
#10 ANe=28'd103584; //R=25, error bit=16
#10 ANe=28'd169120; //R=21, error bit=17
#10 ANe=28'd300192; //R=13, error bit=18
#10 ANe=28'd562336; //R=26, error bit=19
#10 ANe=28'd1086624; //R=23, error bit=20
#10 ANe=28'd2135200; //R=17, error bit=21
#10 ANe=28'd4232352; //R=5, error bit=22
#10 ANe=28'd8426656; //R=10, error bit=23
#10 ANe=28'd16815264; //R=20, error bit=24
#10 ANe=28'd33592480; //R=11, error bit=25
#10 ANe=28'd67146912; //R=22, error bit=26
#10 ANe=28'd134255776; //R=15, error bit=27
#10 ANe=28'd38016; //R=26, error bit=5
#10 ANe=28'd37920; //R=17, error bit=7
#10 ANe=28'd37024; //R=20, error bit=10
#10 ANe=28'd33952; //R=22, error bit=12
#10 ANe=28'd5280; //R=2, error bit=15
#10 $finish;
end
endmodule

Tools/Verilog/ANcodesDecoder/files/Alter_20221007_1058/A29N1312.vcd
$date
	Fri Oct 07 10:58:15 2022
$end
$version
	Icarus Verilog
$end
$timescale
	1s
$end
$scope module ANdecoder_tb $end
$var wire 23 ! Nc [22:0] $end
$var reg 28 " ANe [27:0] $end
$scope module D0 $end
$var wire 28 # ANe [27:0] $end
$var wire 5 $ not_mod_tri [4:0] $end
$var wire 28 % notR [27:0] $end
$var wire 5 & mod_tri [4:0] $end
$var wire 5 ' check [4:0] $end
$var wire 28 ( R [27:0] $end
$var wire 23 ) Nc [22:0] $end
$var wire 28 * ANc2 [27:0] $end
$var wire 28 + ANc1 [27:0] $end
$var wire 28 , ANc [27:0] $end
$upscope $end
$upscope $end
$enddefinitions $end
#0
$dumpvars
b1001010010100000 ,
b1001010010100000 +
b1101010010100001 *
b10100100000 )
b1 (
b0 '
b1 &
b1111111111111111111111111110 %
b11110 $
b1001010010100001 #
b1001010010100001 "
b10100100000 !
$end
#10
b1111111111111111111111111101 %
b10100100000 !
b10100100000 )
b10 (
b11101 $
b0 '
b1001010010100000 ,
b1001010010100000 +
b1001010010100010 *
b10 &
b1001010010100010 "
b1001010010100010 #
#20
b10100100000 !
b10100100000 )
b1111111111111111111111110111 %
b1000 (
b11011 $
b0 '
b1001010010100000 ,
b1001010010100000 +
b11001010010100100 *
b100 &
b1001010010100100 "
b1001010010100100 #
#30
b1111111111111111111101111111 %
b10100100000 !
b10100100000 )
b10000000 (
b10111 $
b0 '
b1001010010100000 ,
b1001010010100000 +
b101001010010101000 *
b1000 &
b1001010010101000 "
b1001010010101000 #
#40
b1111111111110111111111111111 %
b10100100000 !
b10100100000 )
b1000000000000000 (
b1111 $
b0 '
b1001010010100000 ,
b1001010010100000 +
b1001001010010110000 *
b10000 &
b1001010010110000 "
b1001010010110000 #
#50
b1111111111111111111111011111 %
b100000 (
b10100100000 !
b10100100000 )
b11001 $
b0 '
b1001010010100000 ,
b1001010010100000 +
b100001001010011100000 *
b110 &
b1001010011100000 "
b1001010011100000 #
#60
b1111011111111111111111111111 %
b100000000000000000000000 (
b10100100000 !
b10100100000 )
b111 $
b0 '
b1001010010100000 ,
b1001010010100000 +
b10000001001010110100000 *
b11000 &
b1001010110100000 "
b1001010110100000 #
#70
b1111111110111111111111111111 %
b1000000000000000000 (
b10100100000 !
b10100100000 )
b1100 $
b0 '
b1001010010100000 ,
b1001010010100000 +
b100000001001011010100000 *
b10011 &
b1001011010100000 "
b1001011010100000 #
#80
b1111111111011111111111111111 %
b100000000000000000 (
b10100100000 !
b10100100000 )
b1101 $
b0 '
b1001010010100000 ,
b1001010010100000 +
b10000000001001110010100000 *
b10010 &
b1001110010100000 "
b1001110010100000 #
#90
b1111111111111101111111111111 %
b10000000000000 (
b10100100000 !
b10100100000 )
b10001 $
b0 '
b1001010010100000 ,
b1001010010100000 +
b1000000000001011010010100000 *
b1110 &
b1011010010100000 "
b1011010010100000 #
#100
b111111111111111111111111111 %
b1000000000000000000000000000 (
b10100100000 !
b10100100000 )
b11 $
b0 '
b1001010010100000 ,
b1001010010100000 +
b1101010010100001 *
b11100 &
b1101010010100000 "
b1101010010100000 #
#110
b1110111111111111111111111111 %
b1000000000000000000000000 (
b10100100000 !
b10100100000 )
b110 $
b0 '
b1001010010100000 ,
b1001010010100000 +
b11001010010100100 *
b11001 &
b11001010010100000 "
b11001010010100000 #
#120
b1111111011111111111111111111 %
b100000000000000000000 (
b10100100000 !
b10100100000 )
b1010 $
b0 '
b1001010010100000 ,
b1001010010100000 +
b101001010010101000 *
b10101 &
b101001010010100000 "
b101001010010100000 #
#130
b1111111111111110111111111111 %
b1000000000000 (
b10100100000 !
b10100100000 )
b10010 $
b0 '
b1001010010100000 ,
b1001010010100000 +
b1001001010010110000 *
b1101 &
b1001001010010100000 "
b1001001010010100000 #
#140
b1101111111111111111111111111 %
b10000000000000000000000000 (
b10100100000 !
b10100100000 )
b101 $
b0 '
b1001010010100000 ,
b1001010010100000 +
b10001001010010100000 *
b11010 &
b10001001010010100000 "
b10001001010010100000 #
#150
b1111101111111111111111111111 %
b10000000000000000000000 (
b10100100000 !
b10100100000 )
b1000 $
b0 '
b1001010010100000 ,
b1001010010100000 +
b100001001010011100000 *
b10111 &
b100001001010010100000 "
b100001001010010100000 #
#160
b1111111111101111111111111111 %
b10000000000000000 (
b10100100000 !
b10100100000 )
b1110 $
b0 '
b1001010010100000 ,
b1001010010100000 +
b1000001001010010100000 *
b10001 &
b1000001001010010100000 "
b1000001001010010100000 #
#170
b1111111111111111111111101111 %
b10000 (
b10100100000 !
b10100100000 )
b11010 $
b0 '
b1001010010100000 ,
b1001010010100000 +
b10000001001010110100000 *
b101 &
b10000001001010010100000 "
b10000001001010010100000 #
#180
b1111111111111111110111111111 %
b1000000000 (
b10100100000 !
b10100100000 )
b10101 $
b0 '
b1001010010100000 ,
b1001010010100000 +
b100000001001011010100000 *
b1010 &
b100000001001010010100000 "
b100000001001010010100000 #
#190
b1111111101111111111111111111 %
b10000000000000000000 (
b10100100000 !
b10100100000 )
b1011 $
b0 '
b1001010010100000 ,
b1001010010100000 +
b1000000001001010010100000 *
b10100 &
b1000000001001010010100000 "
b1000000001001010010100000 #
#200
b1111111111111111101111111111 %
b10000000000 (
b10100100000 !
b10100100000 )
b10100 $
b0 '
b1001010010100000 ,
b1001010010100000 +
b10000000001001110010100000 *
b1011 &
b10000000001001010010100000 "
b10000000001001010010100000 #
#210
b1111110111111111111111111111 %
b1000000000000000000000 (
b10100100000 !
b10100100000 )
b1001 $
b0 '
b1001010010100000 ,
b1001010010100000 +
b100000000001001010010100000 *
b10110 &
b100000000001001010010100000 "
b100000000001001010010100000 #
#220
b1111111111111011111111111111 %
b100000000000000 (
b10100100000 !
b10100100000 )
b10000 $
b0 '
b1001010010100000 ,
b1001010010100000 +
b1000000000001011010010100000 *
b1111 &
b1000000000001001010010100000 "
b1000000000001001010010100000 #
#230
b1101111111111111111111111111 %
b10000000000000000000000000 (
b10100100000 !
b10100100000 )
b101 $
b11010 '
b1001010010100000 ,
b1001010010000000 +
b1001010010100000 *
b11010 &
b1001010010000000 "
b1001010010000000 #
#240
b1111111111101111111111111111 %
b10000000000000000 (
b10100100000 !
b10100100000 )
b1110 $
b10001 '
b1001010010100000 ,
b1001010000100000 +
b1001010010100000 *
b10001 &
b1001010000100000 "
b1001010000100000 #
#250
b1111111101111111111111111111 %
b10000000000000000000 (
b10100100000 !
b10100100000 )
b1011 $
b10100 '
b1001010010100000 ,
b1001000010100000 +
b1001010010100000 *
b10100 &
b1001000010100000 "
b1001000010100000 #
#260
b1111110111111111111111111111 %
b1000000000000000000000 (
b10100100000 !
b10100100000 )
b1001 $
b10110 '
b1001010010100000 ,
b1000010010100000 +
b1001010010100000 *
b10110 &
b1000010010100000 "
b1000010010100000 #
#270
b1111111111111111111111111101 %
b10 (
b10100100000 !
b10100100000 )
b11101 $
b10 '
b1001010010100000 ,
b1010010100000 +
b1001010010100000 *
b10 &
b1010010100000 "
b1010010100000 #
