Tools/Verilog/ANcodesDecoder/files/AWE_20221006_1501/ANdecoder_AWE_47_for_N_1343.v
// File Name: ./files/AWE_20221006_1501/ANdecoder_AWE_47_for_N_1343.v
// module= 47
// 可更正AN的bit數= 23
// mod的bit數= 6
// 可更正N的bit數= 17

module ANdecoder(numX, out);
input [22:0] numX;
output [16:0] out;
wire [5:0] mod_tri;
wire [5:0] not_mod_tri;
wire [22:0] error_bit;
wire [45:0] and_out;
wire add;
wire [22:0] AN;

assign mod_tri = numX % 47;

//not gate
not not_0(not_mod_tri[0], mod_tri[0]);
not not_1(not_mod_tri[1], mod_tri[1]);
not not_2(not_mod_tri[2], mod_tri[2]);
not not_3(not_mod_tri[3], mod_tri[3]);
not not_4(not_mod_tri[4], mod_tri[4]);
not not_5(not_mod_tri[5], mod_tri[5]);
//and gate
and and_1(and_out[0], mod_tri[0], not_mod_tri[1], not_mod_tri[2], not_mod_tri[3], not_mod_tri[4], not_mod_tri[5]);
and and_2(and_out[1], not_mod_tri[0], mod_tri[1], not_mod_tri[2], not_mod_tri[3], not_mod_tri[4], not_mod_tri[5]);
and and_3(and_out[2], mod_tri[0], mod_tri[1], not_mod_tri[2], not_mod_tri[3], not_mod_tri[4], not_mod_tri[5]);
and and_4(and_out[3], not_mod_tri[0], not_mod_tri[1], mod_tri[2], not_mod_tri[3], not_mod_tri[4], not_mod_tri[5]);
and and_5(and_out[4], mod_tri[0], not_mod_tri[1], mod_tri[2], not_mod_tri[3], not_mod_tri[4], not_mod_tri[5]);
and and_6(and_out[5], not_mod_tri[0], mod_tri[1], mod_tri[2], not_mod_tri[3], not_mod_tri[4], not_mod_tri[5]);
and and_7(and_out[6], mod_tri[0], mod_tri[1], mod_tri[2], not_mod_tri[3], not_mod_tri[4], not_mod_tri[5]);
and and_8(and_out[7], not_mod_tri[0], not_mod_tri[1], not_mod_tri[2], mod_tri[3], not_mod_tri[4], not_mod_tri[5]);
and and_9(and_out[8], mod_tri[0], not_mod_tri[1], not_mod_tri[2], mod_tri[3], not_mod_tri[4], not_mod_tri[5]);
and and_10(and_out[9], not_mod_tri[0], mod_tri[1], not_mod_tri[2], mod_tri[3], not_mod_tri[4], not_mod_tri[5]);
and and_11(and_out[10], mod_tri[0], mod_tri[1], not_mod_tri[2], mod_tri[3], not_mod_tri[4], not_mod_tri[5]);
and and_12(and_out[11], not_mod_tri[0], not_mod_tri[1], mod_tri[2], mod_tri[3], not_mod_tri[4], not_mod_tri[5]);
and and_13(and_out[12], mod_tri[0], not_mod_tri[1], mod_tri[2], mod_tri[3], not_mod_tri[4], not_mod_tri[5]);
and and_14(and_out[13], not_mod_tri[0], mod_tri[1], mod_tri[2], mod_tri[3], not_mod_tri[4], not_mod_tri[5]);
and and_15(and_out[14], mod_tri[0], mod_tri[1], mod_tri[2], mod_tri[3], not_mod_tri[4], not_mod_tri[5]);
and and_16(and_out[15], not_mod_tri[0], not_mod_tri[1], not_mod_tri[2], not_mod_tri[3], mod_tri[4], not_mod_tri[5]);
and and_17(and_out[16], mod_tri[0], not_mod_tri[1], not_mod_tri[2], not_mod_tri[3], mod_tri[4], not_mod_tri[5]);
and and_18(and_out[17], not_mod_tri[0], mod_tri[1], not_mod_tri[2], not_mod_tri[3], mod_tri[4], not_mod_tri[5]);
and and_19(and_out[18], mod_tri[0], mod_tri[1], not_mod_tri[2], not_mod_tri[3], mod_tri[4], not_mod_tri[5]);
and and_20(and_out[19], not_mod_tri[0], not_mod_tri[1], mod_tri[2], not_mod_tri[3], mod_tri[4], not_mod_tri[5]);
and and_21(and_out[20], mod_tri[0], not_mod_tri[1], mod_tri[2], not_mod_tri[3], mod_tri[4], not_mod_tri[5]);
and and_22(and_out[21], not_mod_tri[0], mod_tri[1], mod_tri[2], not_mod_tri[3], mod_tri[4], not_mod_tri[5]);
and and_23(and_out[22], mod_tri[0], mod_tri[1], mod_tri[2], not_mod_tri[3], mod_tri[4], not_mod_tri[5]);
and and_24(and_out[23], not_mod_tri[0], not_mod_tri[1], not_mod_tri[2], mod_tri[3], mod_tri[4], not_mod_tri[5]);
and and_25(and_out[24], mod_tri[0], not_mod_tri[1], not_mod_tri[2], mod_tri[3], mod_tri[4], not_mod_tri[5]);
and and_26(and_out[25], not_mod_tri[0], mod_tri[1], not_mod_tri[2], mod_tri[3], mod_tri[4], not_mod_tri[5]);
and and_27(and_out[26], mod_tri[0], mod_tri[1], not_mod_tri[2], mod_tri[3], mod_tri[4], not_mod_tri[5]);
and and_28(and_out[27], not_mod_tri[0], not_mod_tri[1], mod_tri[2], mod_tri[3], mod_tri[4], not_mod_tri[5]);
and and_29(and_out[28], mod_tri[0], not_mod_tri[1], mod_tri[2], mod_tri[3], mod_tri[4], not_mod_tri[5]);
and and_30(and_out[29], not_mod_tri[0], mod_tri[1], mod_tri[2], mod_tri[3], mod_tri[4], not_mod_tri[5]);
and and_31(and_out[30], mod_tri[0], mod_tri[1], mod_tri[2], mod_tri[3], mod_tri[4], not_mod_tri[5]);
and and_32(and_out[31], not_mod_tri[0], not_mod_tri[1], not_mod_tri[2], not_mod_tri[3], not_mod_tri[4], mod_tri[5]);
and and_33(and_out[32], mod_tri[0], not_mod_tri[1], not_mod_tri[2], not_mod_tri[3], not_mod_tri[4], mod_tri[5]);
and and_34(and_out[33], not_mod_tri[0], mod_tri[1], not_mod_tri[2], not_mod_tri[3], not_mod_tri[4], mod_tri[5]);
and and_35(and_out[34], mod_tri[0], mod_tri[1], not_mod_tri[2], not_mod_tri[3], not_mod_tri[4], mod_tri[5]);
and and_36(and_out[35], not_mod_tri[0], not_mod_tri[1], mod_tri[2], not_mod_tri[3], not_mod_tri[4], mod_tri[5]);
and and_37(and_out[36], mod_tri[0], not_mod_tri[1], mod_tri[2], not_mod_tri[3], not_mod_tri[4], mod_tri[5]);
and and_38(and_out[37], not_mod_tri[0], mod_tri[1], mod_tri[2], not_mod_tri[3], not_mod_tri[4], mod_tri[5]);
and and_39(and_out[38], mod_tri[0], mod_tri[1], mod_tri[2], not_mod_tri[3], not_mod_tri[4], mod_tri[5]);
and and_40(and_out[39], not_mod_tri[0], not_mod_tri[1], not_mod_tri[2], mod_tri[3], not_mod_tri[4], mod_tri[5]);
and and_41(and_out[40], mod_tri[0], not_mod_tri[1], not_mod_tri[2], mod_tri[3], not_mod_tri[4], mod_tri[5]);
and and_42(and_out[41], not_mod_tri[0], mod_tri[1], not_mod_tri[2], mod_tri[3], not_mod_tri[4], mod_tri[5]);
and and_43(and_out[42], mod_tri[0], mod_tri[1], not_mod_tri[2], mod_tri[3], not_mod_tri[4], mod_tri[5]);
and and_44(and_out[43], not_mod_tri[0], not_mod_tri[1], mod_tri[2], mod_tri[3], not_mod_tri[4], mod_tri[5]);
and and_45(and_out[44], mod_tri[0], not_mod_tri[1], mod_tri[2], mod_tri[3], not_mod_tri[4], mod_tri[5]);
and and_46(and_out[45], not_mod_tri[0], mod_tri[1], mod_tri[2], mod_tri[3], not_mod_tri[4], mod_tri[5]);
//or gate
or or_0(error_bit[0], and_out[0], and_out[45]);
or or_1(error_bit[1], and_out[1], and_out[44]);
or or_2(error_bit[2], and_out[3], and_out[42]);
or or_3(error_bit[3], and_out[7], and_out[38]);
or or_4(error_bit[4], and_out[15], and_out[30]);
or or_5(error_bit[5], and_out[14], and_out[31]);
or or_6(error_bit[6], and_out[16], and_out[29]);
or or_7(error_bit[7], and_out[12], and_out[33]);
or or_8(error_bit[8], and_out[20], and_out[25]);
or or_9(error_bit[9], and_out[4], and_out[41]);
or or_10(error_bit[10], and_out[9], and_out[36]);
or or_11(error_bit[11], and_out[19], and_out[26]);
or or_12(error_bit[12], and_out[6], and_out[39]);
or or_13(error_bit[13], and_out[13], and_out[32]);
or or_14(error_bit[14], and_out[18], and_out[27]);
or or_15(error_bit[15], and_out[8], and_out[37]);
or or_16(error_bit[16], and_out[17], and_out[28]);
or or_17(error_bit[17], and_out[10], and_out[35]);
or or_18(error_bit[18], and_out[21], and_out[24]);
or or_19(error_bit[19], and_out[2], and_out[43]);
or or_20(error_bit[20], and_out[5], and_out[40]);
or or_21(error_bit[21], and_out[11], and_out[34]);
or or_22(error_bit[22], and_out[22], and_out[23]);
or or_23(add, and_out[45], and_out[44], and_out[42], and_out[38], and_out[30], and_out[14], and_out[29], and_out[12], and_out[25], and_out[4], and_out[9], and_out[19], and_out[39], and_out[32], and_out[18], and_out[37], and_out[28], and_out[10], and_out[21], and_out[43], and_out[40], and_out[34], and_out[22]);

assign AN = (add==0) ? numX-error_bit : numX+error_bit;

assign out = AN / 47;

endmodule

Tools/Verilog/ANcodesDecoder/files/AWE_20221006_1501/ANdecoder_AWE_47_tb_for_N_1343.v
// File Name: ./files/AWE_20221006_1501/ANdecoder_AWE_47_tb_for_N_1343.v
// module= 47
// N= 1343

module ANdecoder_tb;
reg [22:0] numX;
wire [16:0] out;

ANdecoder D0(numX, out);
initial begin
$dumpfile("./files/AWE_20221006_1501/A47N1343.vcd"); 
$dumpvars(0, ANdecoder_tb);

numX=23'd0;

numX=23'd63122; //R=1, error bit=0
#10 numX=23'd63123; //R=2, error bit=1
#10 numX=23'd63125; //R=4, error bit=2
#10 numX=23'd63129; //R=8, error bit=3
#10 numX=23'd63137; //R=16, error bit=4
#10 numX=23'd63153; //R=32, error bit=5
#10 numX=23'd63185; //R=17, error bit=6
#10 numX=23'd63249; //R=34, error bit=7
#10 numX=23'd63377; //R=21, error bit=8
#10 numX=23'd63633; //R=42, error bit=9
#10 numX=23'd64145; //R=37, error bit=10
#10 numX=23'd65169; //R=27, error bit=11
#10 numX=23'd67217; //R=7, error bit=12
#10 numX=23'd71313; //R=14, error bit=13
#10 numX=23'd79505; //R=28, error bit=14
#10 numX=23'd95889; //R=9, error bit=15
#10 numX=23'd128657; //R=18, error bit=16
#10 numX=23'd194193; //R=36, error bit=17
#10 numX=23'd325265; //R=25, error bit=18
#10 numX=23'd587409; //R=3, error bit=19
#10 numX=23'd1111697; //R=6, error bit=20
#10 numX=23'd2160273; //R=12, error bit=21
#10 numX=23'd4257425; //R=24, error bit=22
#10 numX=23'd63120; //R=46, error bit=0
#10 numX=23'd63119; //R=45, error bit=1
#10 numX=23'd63117; //R=43, error bit=2
#10 numX=23'd63113; //R=39, error bit=3
#10 numX=23'd63105; //R=31, error bit=4
#10 numX=23'd63089; //R=15, error bit=5
#10 numX=23'd63057; //R=30, error bit=6
#10 numX=23'd62993; //R=13, error bit=7
#10 numX=23'd62865; //R=26, error bit=8
#10 numX=23'd62609; //R=5, error bit=9
#10 numX=23'd62097; //R=10, error bit=10
#10 numX=23'd61073; //R=20, error bit=11
#10 numX=23'd59025; //R=40, error bit=12
#10 numX=23'd54929; //R=33, error bit=13
#10 numX=23'd46737; //R=19, error bit=14
#10 numX=23'd30353; //R=38, error bit=15
//ANe=-2415(璽计), R=29, error bit=16
//ANe=-67951(璽计), R=11, error bit=17
//ANe=-199023(璽计), R=22, error bit=18
//ANe=-461167(璽计), R=44, error bit=19
//ANe=-985455(璽计), R=41, error bit=20
//ANe=-2034031(璽计), R=35, error bit=21
//ANe=-4131183(璽计), R=23, error bit=22
#10 $finish;
end
endmodule

Tools/Verilog/ANcodesDecoder/files/AWE_20221006_1501/A47N1343.vcd
$date
	Thu Oct 06 15:01:58 2022
$end
$version
	Icarus Verilog
$end
$timescale
	1s
$end
$scope module ANdecoder_tb $end
$var wire 17 ! out [16:0] $end
$var reg 23 " numX [22:0] $end
$scope module D0 $end
$var wire 1 # add $end
$var wire 23 $ numX [22:0] $end
$var wire 17 % out [16:0] $end
$var wire 6 & not_mod_tri [5:0] $end
$var wire 6 ' mod_tri [5:0] $end
$var wire 23 ( error_bit [22:0] $end
$var wire 46 ) and_out [45:0] $end
$var wire 23 * AN [22:0] $end
$upscope $end
$upscope $end
$enddefinitions $end
#0
$dumpvars
b1111011010010001 *
b1 )
b1 (
b1 '
b111110 &
b10100111111 %
b1111011010010010 $
0#
b1111011010010010 "
b10100111111 !
$end
#10
b10 (
b10 )
b111101 &
b10 '
b1111011010010001 *
b1111011010010011 "
b1111011010010011 $
#20
b100 (
b1000 )
b111011 &
b100 '
b1111011010010001 *
b1111011010010101 "
b1111011010010101 $
#30
b1000 (
b10000000 )
b110111 &
b1000 '
b1111011010010001 *
b1111011010011001 "
b1111011010011001 $
#40
b10000 (
b1000000000000000 )
b101111 &
b10000 '
b1111011010010001 *
b1111011010100001 "
b1111011010100001 $
#50
b100000 (
b10000000000000000000000000000000 )
b11111 &
b100000 '
b1111011010010001 *
b1111011010110001 "
b1111011010110001 $
#60
b10100111111 !
b10100111111 %
b1000000 (
b10000000000000000 )
b101110 &
b10001 '
b1111011010010001 *
b1111011011010001 "
b1111011011010001 $
#70
b10000000 (
b1000000000000000000000000000000000 )
b11101 &
b10100111111 !
b10100111111 %
b100010 '
b1111011010010001 *
b1111011100010001 "
b1111011100010001 $
#80
b100000000 (
b100000000000000000000 )
b101010 &
b10100111111 !
b10100111111 %
b10101 '
b1111011010010001 *
b1111011110010001 "
b1111011110010001 $
#90
b1000000000 (
b100000000000000000000000000000000000000000 )
b10101 &
b10100111111 !
b10100111111 %
b101010 '
b1111011010010001 *
b1111100010010001 "
b1111100010010001 $
#100
b10000000000 (
b1000000000000000000000000000000000000 )
b11010 &
b10100111111 !
b10100111111 %
b100101 '
b1111011010010001 *
b1111101010010001 "
b1111101010010001 $
#110
b100000000000 (
b100000000000000000000000000 )
b100100 &
b10100111111 !
b10100111111 %
b11011 '
b1111011010010001 *
b1111111010010001 "
b1111111010010001 $
#120
b1000000000000 (
b1000000 )
b111000 &
b10100111111 !
b10100111111 %
b111 '
b1111011010010001 *
b10000011010010001 "
b10000011010010001 $
#130
b10000000000000 (
b10000000000000 )
b110001 &
b10100111111 !
b10100111111 %
b1110 '
b1111011010010001 *
b10001011010010001 "
b10001011010010001 $
#140
b100000000000000 (
b1000000000000000000000000000 )
b100011 &
b10100111111 !
b10100111111 %
b11100 '
b1111011010010001 *
b10011011010010001 "
b10011011010010001 $
#150
b1000000000000000 (
b100000000 )
b110110 &
b10100111111 !
b10100111111 %
b1001 '
b1111011010010001 *
b10111011010010001 "
b10111011010010001 $
#160
b10000000000000000 (
b100000000000000000 )
b101101 &
b10100111111 !
b10100111111 %
b10010 '
b1111011010010001 *
b11111011010010001 "
b11111011010010001 $
#170
b100000000000000000 (
b100000000000000000000000000000000000 )
b11011 &
b10100111111 !
b10100111111 %
b100100 '
b1111011010010001 *
b101111011010010001 "
b101111011010010001 $
#180
b1000000000000000000 (
b1000000000000000000000000 )
b100110 &
b10100111111 !
b10100111111 %
b11001 '
b1111011010010001 *
b1001111011010010001 "
b1001111011010010001 $
#190
b10000000000000000000 (
b100 )
b111100 &
b10100111111 !
b10100111111 %
b11 '
b1111011010010001 *
b10001111011010010001 "
b10001111011010010001 $
#200
b100000000000000000000 (
b100000 )
b111001 &
b10100111111 !
b10100111111 %
b110 '
b1111011010010001 *
b100001111011010010001 "
b100001111011010010001 $
#210
b1000000000000000000000 (
b100000000000 )
b110011 &
b10100111111 !
b10100111111 %
b1100 '
b1111011010010001 *
b1000001111011010010001 "
b1000001111011010010001 $
#220
b10000000000000000000000 (
b100000000000000000000000 )
b100111 &
b10100111111 !
b10100111111 %
b11000 '
b1111011010010001 *
b10000001111011010010001 "
b10000001111011010010001 $
#230
1#
b1 (
b1000000000000000000000000000000000000000000000 )
b10001 &
b10100111111 !
b10100111111 %
b101110 '
b1111011010010001 *
b1111011010010000 "
b1111011010010000 $
#240
1#
b10 (
b100000000000000000000000000000000000000000000 )
b10010 &
b10100111111 !
b10100111111 %
b101101 '
b1111011010010001 *
b1111011010001111 "
b1111011010001111 $
#250
1#
b100 (
b1000000000000000000000000000000000000000000 )
b10100 &
b10100111111 !
b10100111111 %
b101011 '
b1111011010010001 *
b1111011010001101 "
b1111011010001101 $
#260
1#
b1000 (
b100000000000000000000000000000000000000 )
b11000 &
b10100111111 !
b10100111111 %
b100111 '
b1111011010010001 *
b1111011010001001 "
b1111011010001001 $
#270
1#
b10000 (
b1000000000000000000000000000000 )
b100000 &
b10100111111 !
b10100111111 %
b11111 '
b1111011010010001 *
b1111011010000001 "
b1111011010000001 $
#280
1#
b100000 (
b100000000000000 )
b110000 &
b10100111111 !
b10100111111 %
b1111 '
b1111011010010001 *
b1111011001110001 "
b1111011001110001 $
#290
1#
b1000000 (
b100000000000000000000000000000 )
b100001 &
b10100111111 !
b10100111111 %
b11110 '
b1111011010010001 *
b1111011001010001 "
b1111011001010001 $
#300
1#
b10000000 (
b1000000000000 )
b110010 &
b10100111111 !
b10100111111 %
b1101 '
b1111011010010001 *
b1111011000010001 "
b1111011000010001 $
#310
1#
b100000000 (
b10000000000000000000000000 )
b100101 &
b10100111111 !
b10100111111 %
b11010 '
b1111011010010001 *
b1111010110010001 "
b1111010110010001 $
#320
1#
b1000000000 (
b10000 )
b111010 &
b10100111111 !
b10100111111 %
b101 '
b1111011010010001 *
b1111010010010001 "
b1111010010010001 $
#330
1#
b10000000000 (
b1000000000 )
b110101 &
b10100111111 !
b10100111111 %
b1010 '
b1111011010010001 *
b1111001010010001 "
b1111001010010001 $
#340
1#
b100000000000 (
b10000000000000000000 )
b101011 &
b10100111111 !
b10100111111 %
b10100 '
b1111011010010001 *
b1110111010010001 "
b1110111010010001 $
#350
1#
b1000000000000 (
b1000000000000000000000000000000000000000 )
b10111 &
b10100111111 !
b10100111111 %
b101000 '
b1111011010010001 *
b1110011010010001 "
b1110011010010001 $
#360
1#
b10000000000000 (
b100000000000000000000000000000000 )
b11110 &
b10100111111 !
b10100111111 %
b100001 '
b1111011010010001 *
b1101011010010001 "
b1101011010010001 $
#370
1#
b100000000000000 (
b1000000000000000000 )
b101100 &
b10100111111 !
b10100111111 %
b10011 '
b1111011010010001 *
b1011011010010001 "
b1011011010010001 $
#380
1#
b1000000000000000 (
b10000000000000000000000000000000000000 )
b11001 &
b10100111111 !
b10100111111 %
b100110 '
b1111011010010001 *
b111011010010001 "
b111011010010001 $
