Tools/Verilog/ANcodesDecoder/files/AWE_20221007_1058/ANdecoder_AWE_37_for_N_564.v
// File Name: ./files/AWE_20221007_1058/ANdecoder_AWE_37_for_N_564.v
// module= 37
// 可更正AN的bit數= 18
// mod的bit數= 6
// 可更正N的bit數= 12

module ANdecoder(ANe, Nc);
input [17:0] ANe;
output [11:0] Nc;
wire [5:0] mod_tri;
wire [5:0] not_mod_tri;
wire [17:0] error_bit;
wire [35:0] and_out;
wire add;
wire [17:0] ANc;

assign mod_tri = ANe % 37;

//not gate
not not_0(not_mod_tri[0], mod_tri[0]);
not not_1(not_mod_tri[1], mod_tri[1]);
not not_2(not_mod_tri[2], mod_tri[2]);
not not_3(not_mod_tri[3], mod_tri[3]);
not not_4(not_mod_tri[4], mod_tri[4]);
not not_5(not_mod_tri[5], mod_tri[5]);
//and gate
and and_1(and_out[0], mod_tri[0], not_mod_tri[1], not_mod_tri[2], not_mod_tri[3], not_mod_tri[4], not_mod_tri[5]);
and and_2(and_out[1], not_mod_tri[0], mod_tri[1], not_mod_tri[2], not_mod_tri[3], not_mod_tri[4], not_mod_tri[5]);
and and_3(and_out[2], mod_tri[0], mod_tri[1], not_mod_tri[2], not_mod_tri[3], not_mod_tri[4], not_mod_tri[5]);
and and_4(and_out[3], not_mod_tri[0], not_mod_tri[1], mod_tri[2], not_mod_tri[3], not_mod_tri[4], not_mod_tri[5]);
and and_5(and_out[4], mod_tri[0], not_mod_tri[1], mod_tri[2], not_mod_tri[3], not_mod_tri[4], not_mod_tri[5]);
and and_6(and_out[5], not_mod_tri[0], mod_tri[1], mod_tri[2], not_mod_tri[3], not_mod_tri[4], not_mod_tri[5]);
and and_7(and_out[6], mod_tri[0], mod_tri[1], mod_tri[2], not_mod_tri[3], not_mod_tri[4], not_mod_tri[5]);
and and_8(and_out[7], not_mod_tri[0], not_mod_tri[1], not_mod_tri[2], mod_tri[3], not_mod_tri[4], not_mod_tri[5]);
and and_9(and_out[8], mod_tri[0], not_mod_tri[1], not_mod_tri[2], mod_tri[3], not_mod_tri[4], not_mod_tri[5]);
and and_10(and_out[9], not_mod_tri[0], mod_tri[1], not_mod_tri[2], mod_tri[3], not_mod_tri[4], not_mod_tri[5]);
and and_11(and_out[10], mod_tri[0], mod_tri[1], not_mod_tri[2], mod_tri[3], not_mod_tri[4], not_mod_tri[5]);
and and_12(and_out[11], not_mod_tri[0], not_mod_tri[1], mod_tri[2], mod_tri[3], not_mod_tri[4], not_mod_tri[5]);
and and_13(and_out[12], mod_tri[0], not_mod_tri[1], mod_tri[2], mod_tri[3], not_mod_tri[4], not_mod_tri[5]);
and and_14(and_out[13], not_mod_tri[0], mod_tri[1], mod_tri[2], mod_tri[3], not_mod_tri[4], not_mod_tri[5]);
and and_15(and_out[14], mod_tri[0], mod_tri[1], mod_tri[2], mod_tri[3], not_mod_tri[4], not_mod_tri[5]);
and and_16(and_out[15], not_mod_tri[0], not_mod_tri[1], not_mod_tri[2], not_mod_tri[3], mod_tri[4], not_mod_tri[5]);
and and_17(and_out[16], mod_tri[0], not_mod_tri[1], not_mod_tri[2], not_mod_tri[3], mod_tri[4], not_mod_tri[5]);
and and_18(and_out[17], not_mod_tri[0], mod_tri[1], not_mod_tri[2], not_mod_tri[3], mod_tri[4], not_mod_tri[5]);
and and_19(and_out[18], mod_tri[0], mod_tri[1], not_mod_tri[2], not_mod_tri[3], mod_tri[4], not_mod_tri[5]);
and and_20(and_out[19], not_mod_tri[0], not_mod_tri[1], mod_tri[2], not_mod_tri[3], mod_tri[4], not_mod_tri[5]);
and and_21(and_out[20], mod_tri[0], not_mod_tri[1], mod_tri[2], not_mod_tri[3], mod_tri[4], not_mod_tri[5]);
and and_22(and_out[21], not_mod_tri[0], mod_tri[1], mod_tri[2], not_mod_tri[3], mod_tri[4], not_mod_tri[5]);
and and_23(and_out[22], mod_tri[0], mod_tri[1], mod_tri[2], not_mod_tri[3], mod_tri[4], not_mod_tri[5]);
and and_24(and_out[23], not_mod_tri[0], not_mod_tri[1], not_mod_tri[2], mod_tri[3], mod_tri[4], not_mod_tri[5]);
and and_25(and_out[24], mod_tri[0], not_mod_tri[1], not_mod_tri[2], mod_tri[3], mod_tri[4], not_mod_tri[5]);
and and_26(and_out[25], not_mod_tri[0], mod_tri[1], not_mod_tri[2], mod_tri[3], mod_tri[4], not_mod_tri[5]);
and and_27(and_out[26], mod_tri[0], mod_tri[1], not_mod_tri[2], mod_tri[3], mod_tri[4], not_mod_tri[5]);
and and_28(and_out[27], not_mod_tri[0], not_mod_tri[1], mod_tri[2], mod_tri[3], mod_tri[4], not_mod_tri[5]);
and and_29(and_out[28], mod_tri[0], not_mod_tri[1], mod_tri[2], mod_tri[3], mod_tri[4], not_mod_tri[5]);
and and_30(and_out[29], not_mod_tri[0], mod_tri[1], mod_tri[2], mod_tri[3], mod_tri[4], not_mod_tri[5]);
and and_31(and_out[30], mod_tri[0], mod_tri[1], mod_tri[2], mod_tri[3], mod_tri[4], not_mod_tri[5]);
and and_32(and_out[31], not_mod_tri[0], not_mod_tri[1], not_mod_tri[2], not_mod_tri[3], not_mod_tri[4], mod_tri[5]);
and and_33(and_out[32], mod_tri[0], not_mod_tri[1], not_mod_tri[2], not_mod_tri[3], not_mod_tri[4], mod_tri[5]);
and and_34(and_out[33], not_mod_tri[0], mod_tri[1], not_mod_tri[2], not_mod_tri[3], not_mod_tri[4], mod_tri[5]);
and and_35(and_out[34], mod_tri[0], mod_tri[1], not_mod_tri[2], not_mod_tri[3], not_mod_tri[4], mod_tri[5]);
and and_36(and_out[35], not_mod_tri[0], not_mod_tri[1], mod_tri[2], not_mod_tri[3], not_mod_tri[4], mod_tri[5]);
//or gate
or or_0(error_bit[0], and_out[0], and_out[35]);
or or_1(error_bit[1], and_out[1], and_out[34]);
or or_2(error_bit[2], and_out[3], and_out[32]);
or or_3(error_bit[3], and_out[7], and_out[28]);
or or_4(error_bit[4], and_out[15], and_out[20]);
or or_5(error_bit[5], and_out[4], and_out[31]);
or or_6(error_bit[6], and_out[9], and_out[26]);
or or_7(error_bit[7], and_out[16], and_out[19]);
or or_8(error_bit[8], and_out[2], and_out[33]);
or or_9(error_bit[9], and_out[5], and_out[30]);
or or_10(error_bit[10], and_out[11], and_out[24]);
or or_11(error_bit[11], and_out[12], and_out[23]);
or or_12(error_bit[12], and_out[10], and_out[25]);
or or_13(error_bit[13], and_out[14], and_out[21]);
or or_14(error_bit[14], and_out[6], and_out[29]);
or or_15(error_bit[15], and_out[13], and_out[22]);
or or_16(error_bit[16], and_out[8], and_out[27]);
or or_17(error_bit[17], and_out[17], and_out[18]);
or or_18(add, and_out[35], and_out[34], and_out[32], and_out[28], and_out[20], and_out[4], and_out[9], and_out[19], and_out[2], and_out[5], and_out[11], and_out[23], and_out[10], and_out[21], and_out[6], and_out[13], and_out[27], and_out[18]);

assign ANc = (add==0) ? ANe-error_bit : ANe+error_bit;

assign Nc = ANc / 37;

endmodule

Tools/Verilog/ANcodesDecoder/files/AWE_20221007_1058/ANdecoder_AWE_37_tb_for_N_564.v
// File Name: ./files/AWE_20221007_1058/ANdecoder_AWE_37_tb_for_N_564.v
// module= 37
// N= 564

module ANdecoder_tb;
reg [17:0] ANe;
wire [11:0] Nc;

ANdecoder D0(ANe, Nc);
initial begin
$dumpfile("./files/AWE_20221007_1058/A37N564.vcd"); 
$dumpvars(0, ANdecoder_tb);

ANe=18'd0;

ANe=18'd20869; //R=1, error bit=0
#10 ANe=18'd20870; //R=2, error bit=1
#10 ANe=18'd20872; //R=4, error bit=2
#10 ANe=18'd20876; //R=8, error bit=3
#10 ANe=18'd20884; //R=16, error bit=4
#10 ANe=18'd20900; //R=32, error bit=5
#10 ANe=18'd20932; //R=27, error bit=6
#10 ANe=18'd20996; //R=17, error bit=7
#10 ANe=18'd21124; //R=34, error bit=8
#10 ANe=18'd21380; //R=31, error bit=9
#10 ANe=18'd21892; //R=25, error bit=10
#10 ANe=18'd22916; //R=13, error bit=11
#10 ANe=18'd24964; //R=26, error bit=12
#10 ANe=18'd29060; //R=15, error bit=13
#10 ANe=18'd37252; //R=30, error bit=14
#10 ANe=18'd53636; //R=23, error bit=15
#10 ANe=18'd86404; //R=9, error bit=16
#10 ANe=18'd151940; //R=18, error bit=17
#10 ANe=18'd20867; //R=36, error bit=0
#10 ANe=18'd20866; //R=35, error bit=1
#10 ANe=18'd20864; //R=33, error bit=2
#10 ANe=18'd20860; //R=29, error bit=3
#10 ANe=18'd20852; //R=21, error bit=4
#10 ANe=18'd20836; //R=5, error bit=5
#10 ANe=18'd20804; //R=10, error bit=6
#10 ANe=18'd20740; //R=20, error bit=7
#10 ANe=18'd20612; //R=3, error bit=8
#10 ANe=18'd20356; //R=6, error bit=9
#10 ANe=18'd19844; //R=12, error bit=10
#10 ANe=18'd18820; //R=24, error bit=11
#10 ANe=18'd16772; //R=11, error bit=12
#10 ANe=18'd12676; //R=22, error bit=13
#10 ANe=18'd4484; //R=7, error bit=14
//ANe=-11900(­t¼Æ), R=14, error bit=15
//ANe=-44668(­t¼Æ), R=28, error bit=16
//ANe=-110204(­t¼Æ), R=19, error bit=17
#10 $finish;
end
endmodule

Tools/Verilog/ANcodesDecoder/files/AWE_20221007_1058/A37N564.vcd
$date
	Fri Oct 07 10:58:45 2022
$end
$version
	Icarus Verilog
$end
$timescale
	1s
$end
$scope module ANdecoder_tb $end
$var wire 12 ! Nc [11:0] $end
$var reg 18 " ANe [17:0] $end
$scope module D0 $end
$var wire 18 # ANe [17:0] $end
$var wire 1 $ add $end
$var wire 6 % not_mod_tri [5:0] $end
$var wire 6 & mod_tri [5:0] $end
$var wire 18 ' error_bit [17:0] $end
$var wire 36 ( and_out [35:0] $end
$var wire 12 ) Nc [11:0] $end
$var wire 18 * ANc [17:0] $end
$upscope $end
$upscope $end
$enddefinitions $end
#0
$dumpvars
b101000110000100 *
b1000110100 )
b1 (
b1 '
b1 &
b111110 %
0$
b101000110000101 #
b101000110000101 "
b1000110100 !
$end
#10
b10 '
b10 (
b111101 %
b10 &
b101000110000100 *
b101000110000110 "
b101000110000110 #
#20
b100 '
b1000 (
b111011 %
b100 &
b101000110000100 *
b101000110001000 "
b101000110001000 #
#30
b1000 '
b10000000 (
b110111 %
b1000 &
b101000110000100 *
b101000110001100 "
b101000110001100 #
#40
b10000 '
b1000000000000000 (
b101111 %
b10000 &
b101000110000100 *
b101000110010100 "
b101000110010100 #
#50
b100000 '
b10000000000000000000000000000000 (
b11111 %
b100000 &
b101000110000100 *
b101000110100100 "
b101000110100100 #
#60
b1000110100 !
b1000110100 )
b1000000 '
b100000000000000000000000000 (
b100100 %
b11011 &
b101000110000100 *
b101000111000100 "
b101000111000100 #
#70
b10000000 '
b10000000000000000 (
b101110 %
b1000110100 !
b1000110100 )
b10001 &
b101000110000100 *
b101001000000100 "
b101001000000100 #
#80
b100000000 '
b1000000000000000000000000000000000 (
b11101 %
b1000110100 !
b1000110100 )
b100010 &
b101000110000100 *
b101001010000100 "
b101001010000100 #
#90
b1000000000 '
b1000000000000000000000000000000 (
b100000 %
b1000110100 !
b1000110100 )
b11111 &
b101000110000100 *
b101001110000100 "
b101001110000100 #
#100
b10000000000 '
b1000000000000000000000000 (
b100110 %
b1000110100 !
b1000110100 )
b11001 &
b101000110000100 *
b101010110000100 "
b101010110000100 #
#110
b100000000000 '
b1000000000000 (
b110010 %
b1000110100 !
b1000110100 )
b1101 &
b101000110000100 *
b101100110000100 "
b101100110000100 #
#120
b1000000000000 '
b10000000000000000000000000 (
b100101 %
b1000110100 !
b1000110100 )
b11010 &
b101000110000100 *
b110000110000100 "
b110000110000100 #
#130
b10000000000000 '
b100000000000000 (
b110000 %
b1000110100 !
b1000110100 )
b1111 &
b101000110000100 *
b111000110000100 "
b111000110000100 #
#140
b100000000000000 '
b100000000000000000000000000000 (
b100001 %
b1000110100 !
b1000110100 )
b11110 &
b101000110000100 *
b1001000110000100 "
b1001000110000100 #
#150
b1000000000000000 '
b10000000000000000000000 (
b101000 %
b1000110100 !
b1000110100 )
b10111 &
b101000110000100 *
b1101000110000100 "
b1101000110000100 #
#160
b10000000000000000 '
b100000000 (
b110110 %
b1000110100 !
b1000110100 )
b1001 &
b101000110000100 *
b10101000110000100 "
b10101000110000100 #
#170
b100000000000000000 '
b100000000000000000 (
b101101 %
b1000110100 !
b1000110100 )
b10010 &
b101000110000100 *
b100101000110000100 "
b100101000110000100 #
#180
1$
b1 '
b100000000000000000000000000000000000 (
b11011 %
b1000110100 !
b1000110100 )
b100100 &
b101000110000100 *
b101000110000011 "
b101000110000011 #
#190
1$
b10 '
b10000000000000000000000000000000000 (
b11100 %
b1000110100 !
b1000110100 )
b100011 &
b101000110000100 *
b101000110000010 "
b101000110000010 #
#200
1$
b100 '
b100000000000000000000000000000000 (
b11110 %
b1000110100 !
b1000110100 )
b100001 &
b101000110000100 *
b101000110000000 "
b101000110000000 #
#210
1$
b1000 '
b10000000000000000000000000000 (
b100010 %
b1000110100 !
b1000110100 )
b11101 &
b101000110000100 *
b101000101111100 "
b101000101111100 #
#220
1$
b10000 '
b100000000000000000000 (
b101010 %
b1000110100 !
b1000110100 )
b10101 &
b101000110000100 *
b101000101110100 "
b101000101110100 #
#230
1$
b100000 '
b10000 (
b111010 %
b1000110100 !
b1000110100 )
b101 &
b101000110000100 *
b101000101100100 "
b101000101100100 #
#240
1$
b1000000 '
b1000000000 (
b110101 %
b1000110100 !
b1000110100 )
b1010 &
b101000110000100 *
b101000101000100 "
b101000101000100 #
#250
1$
b10000000 '
b10000000000000000000 (
b101011 %
b1000110100 !
b1000110100 )
b10100 &
b101000110000100 *
b101000100000100 "
b101000100000100 #
#260
1$
b100000000 '
b100 (
b111100 %
b1000110100 !
b1000110100 )
b11 &
b101000110000100 *
b101000010000100 "
b101000010000100 #
#270
1$
b1000000000 '
b100000 (
b111001 %
b1000110100 !
b1000110100 )
b110 &
b101000110000100 *
b100111110000100 "
b100111110000100 #
#280
1$
b10000000000 '
b100000000000 (
b110011 %
b1000110100 !
b1000110100 )
b1100 &
b101000110000100 *
b100110110000100 "
b100110110000100 #
#290
1$
b100000000000 '
b100000000000000000000000 (
b100111 %
b1000110100 !
b1000110100 )
b11000 &
b101000110000100 *
b100100110000100 "
b100100110000100 #
#300
1$
b1000000000000 '
b10000000000 (
b110100 %
b1000110100 !
b1000110100 )
b1011 &
b101000110000100 *
b100000110000100 "
b100000110000100 #
#310
1$
b10000000000000 '
b1000000000000000000000 (
b101001 %
b1000110100 !
b1000110100 )
b10110 &
b101000110000100 *
b11000110000100 "
b11000110000100 #
#320
1$
b100000000000000 '
b1000000 (
b111000 %
b1000110100 !
b1000110100 )
b111 &
b101000110000100 *
b1000110000100 "
b1000110000100 #
