Tools/Verilog/ANcodesDecoder/files/BER_20221007_1058/ANdecoder_BER_29_for_N_123.v
// File Name: ./files/BER_20221007_1058/ANdecoder_BER_29_for_N_123.v
// module= 29
// 可更正AN的bit數= 14
// mod的bit數= 5
// 可更正N的bit數= 9

module ANdecoder(ANe, Nc);
input [13:0] ANe;
output [8:0] Nc;
wire [4:0] mod_tri;
wire [4:0] not_mod_tri;
wire [13:0] error_bit;
wire [27:0] and_out;
wire [13:0] ANc;

assign mod_tri = ANe % 29;

//not gate
not not_0(not_mod_tri[0], mod_tri[0]);
not not_1(not_mod_tri[1], mod_tri[1]);
not not_2(not_mod_tri[2], mod_tri[2]);
not not_3(not_mod_tri[3], mod_tri[3]);
not not_4(not_mod_tri[4], mod_tri[4]);
//and gate
and and_1(and_out[0], mod_tri[0], not_mod_tri[1], not_mod_tri[2], not_mod_tri[3], not_mod_tri[4]);
and and_2(and_out[1], not_mod_tri[0], mod_tri[1], not_mod_tri[2], not_mod_tri[3], not_mod_tri[4]);
and and_3(and_out[2], mod_tri[0], mod_tri[1], not_mod_tri[2], not_mod_tri[3], not_mod_tri[4]);
and and_4(and_out[3], not_mod_tri[0], not_mod_tri[1], mod_tri[2], not_mod_tri[3], not_mod_tri[4]);
and and_5(and_out[4], mod_tri[0], not_mod_tri[1], mod_tri[2], not_mod_tri[3], not_mod_tri[4]);
and and_6(and_out[5], not_mod_tri[0], mod_tri[1], mod_tri[2], not_mod_tri[3], not_mod_tri[4]);
and and_7(and_out[6], mod_tri[0], mod_tri[1], mod_tri[2], not_mod_tri[3], not_mod_tri[4]);
and and_8(and_out[7], not_mod_tri[0], not_mod_tri[1], not_mod_tri[2], mod_tri[3], not_mod_tri[4]);
and and_9(and_out[8], mod_tri[0], not_mod_tri[1], not_mod_tri[2], mod_tri[3], not_mod_tri[4]);
and and_10(and_out[9], not_mod_tri[0], mod_tri[1], not_mod_tri[2], mod_tri[3], not_mod_tri[4]);
and and_11(and_out[10], mod_tri[0], mod_tri[1], not_mod_tri[2], mod_tri[3], not_mod_tri[4]);
and and_12(and_out[11], not_mod_tri[0], not_mod_tri[1], mod_tri[2], mod_tri[3], not_mod_tri[4]);
and and_13(and_out[12], mod_tri[0], not_mod_tri[1], mod_tri[2], mod_tri[3], not_mod_tri[4]);
and and_14(and_out[13], not_mod_tri[0], mod_tri[1], mod_tri[2], mod_tri[3], not_mod_tri[4]);
and and_15(and_out[14], mod_tri[0], mod_tri[1], mod_tri[2], mod_tri[3], not_mod_tri[4]);
and and_16(and_out[15], not_mod_tri[0], not_mod_tri[1], not_mod_tri[2], not_mod_tri[3], mod_tri[4]);
and and_17(and_out[16], mod_tri[0], not_mod_tri[1], not_mod_tri[2], not_mod_tri[3], mod_tri[4]);
and and_18(and_out[17], not_mod_tri[0], mod_tri[1], not_mod_tri[2], not_mod_tri[3], mod_tri[4]);
and and_19(and_out[18], mod_tri[0], mod_tri[1], not_mod_tri[2], not_mod_tri[3], mod_tri[4]);
and and_20(and_out[19], not_mod_tri[0], not_mod_tri[1], mod_tri[2], not_mod_tri[3], mod_tri[4]);
and and_21(and_out[20], mod_tri[0], not_mod_tri[1], mod_tri[2], not_mod_tri[3], mod_tri[4]);
and and_22(and_out[21], not_mod_tri[0], mod_tri[1], mod_tri[2], not_mod_tri[3], mod_tri[4]);
and and_23(and_out[22], mod_tri[0], mod_tri[1], mod_tri[2], not_mod_tri[3], mod_tri[4]);
and and_24(and_out[23], not_mod_tri[0], not_mod_tri[1], not_mod_tri[2], mod_tri[3], mod_tri[4]);
and and_25(and_out[24], mod_tri[0], not_mod_tri[1], not_mod_tri[2], mod_tri[3], mod_tri[4]);
and and_26(and_out[25], not_mod_tri[0], mod_tri[1], not_mod_tri[2], mod_tri[3], mod_tri[4]);
and and_27(and_out[26], mod_tri[0], mod_tri[1], not_mod_tri[2], mod_tri[3], mod_tri[4]);
and and_28(and_out[27], not_mod_tri[0], not_mod_tri[1], mod_tri[2], mod_tri[3], mod_tri[4]);
//or gate
or or_0(error_bit[0], and_out[0], and_out[27]);
or or_1(error_bit[1], and_out[1], and_out[26]);
or or_2(error_bit[2], and_out[3], and_out[24]);
or or_3(error_bit[3], and_out[7], and_out[20]);
or or_4(error_bit[4], and_out[12], and_out[15]);
or or_5(error_bit[5], and_out[2], and_out[25]);
or or_6(error_bit[6], and_out[5], and_out[22]);
or or_7(error_bit[7], and_out[11], and_out[16]);
or or_8(error_bit[8], and_out[4], and_out[23]);
or or_9(error_bit[9], and_out[9], and_out[18]);
or or_10(error_bit[10], and_out[8], and_out[19]);
or or_11(error_bit[11], and_out[10], and_out[17]);
or or_12(error_bit[12], and_out[6], and_out[21]);
or or_13(error_bit[13], and_out[13], and_out[14]);
//xor gate
xor xor_0(ANc[0],error_bit[0],ANe[0]);
xor xor_1(ANc[1],error_bit[1],ANe[1]);
xor xor_2(ANc[2],error_bit[2],ANe[2]);
xor xor_3(ANc[3],error_bit[3],ANe[3]);
xor xor_4(ANc[4],error_bit[4],ANe[4]);
xor xor_5(ANc[5],error_bit[5],ANe[5]);
xor xor_6(ANc[6],error_bit[6],ANe[6]);
xor xor_7(ANc[7],error_bit[7],ANe[7]);
xor xor_8(ANc[8],error_bit[8],ANe[8]);
xor xor_9(ANc[9],error_bit[9],ANe[9]);
xor xor_10(ANc[10],error_bit[10],ANe[10]);
xor xor_11(ANc[11],error_bit[11],ANe[11]);
xor xor_12(ANc[12],error_bit[12],ANe[12]);
xor xor_13(ANc[13],error_bit[13],ANe[13]);
assign Nc = ANc / 29;

endmodule

Tools/Verilog/ANcodesDecoder/files/BER_20221007_1058/ANdecoder_BER_29_tb_for_N_123.v
// File Name: ./files/BER_20221007_1058/ANdecoder_BER_29_tb_for_N_123.v
// module= 29
// N= 123

module ANdecoder_tb;
reg [13:0] ANe;
wire [8:0] Nc;

ANdecoder D0(ANe, Nc);
initial begin
$dumpfile("./files/BER_20221007_1058/A29N123.vcd"); 
$dumpvars(0, ANdecoder_tb);

ANe=14'd3583; //R=16, error bit=4
#10 ANe=14'd4079; //R=19, error bit=9
#10 ANe=14'd7663; //R=7, error bit=12
#10 ANe=14'd11759; //R=14, error bit=13
#10 ANe=14'd3566; //R=28, error bit=0
#10 ANe=14'd3565; //R=27, error bit=1
#10 ANe=14'd3563; //R=25, error bit=2
#10 ANe=14'd3559; //R=21, error bit=3
#10 ANe=14'd3535; //R=26, error bit=5
#10 ANe=14'd3503; //R=23, error bit=6
#10 ANe=14'd3439; //R=17, error bit=7
#10 ANe=14'd3311; //R=5, error bit=8
#10 ANe=14'd2543; //R=20, error bit=10
#10 ANe=14'd1519; //R=11, error bit=11
#10 $finish;
end
endmodule

Tools/Verilog/ANcodesDecoder/files/BER_20221007_1058/A29N123.vcd
$date
	Fri Oct 07 10:58:29 2022
$end
$version
	Icarus Verilog
$end
$timescale
	1s
$end
$scope module ANdecoder_tb $end
$var wire 9 ! Nc [8:0] $end
$var reg 14 " ANe [13:0] $end
$scope module D0 $end
$var wire 14 # ANe [13:0] $end
$var wire 5 $ not_mod_tri [4:0] $end
$var wire 5 % mod_tri [4:0] $end
$var wire 14 & error_bit [13:0] $end
$var wire 28 ' and_out [27:0] $end
$var wire 9 ( Nc [8:0] $end
$var wire 14 ) ANc [13:0] $end
$upscope $end
$upscope $end
$enddefinitions $end
#0
$dumpvars
b110111101111 )
b1111011 (
b1000000000000000 '
b10000 &
b10000 %
b1111 $
b110111111111 #
b110111111111 "
b1111011 !
$end
#10
b1000000000 &
b1000000000000000000 '
b1100 $
b1111011 !
b1111011 (
b110111101111 )
b10011 %
b111111101111 "
b111111101111 #
#20
b1000000000000 &
b1000000 '
b11000 $
b1111011 !
b1111011 (
b110111101111 )
b111 %
b1110111101111 "
b1110111101111 #
#30
b10000000000000 &
b10000000000000 '
b10001 $
b1111011 !
b1111011 (
b110111101111 )
b1110 %
b10110111101111 "
b10110111101111 #
#40
b1 &
b1000000000000000000000000000 '
b11 $
b1111011 !
b1111011 (
b110111101111 )
b11100 %
b110111101110 "
b110111101110 #
#50
b10 &
b100000000000000000000000000 '
b100 $
b1111011 !
b1111011 (
b110111101111 )
b11011 %
b110111101101 "
b110111101101 #
#60
b100 &
b1000000000000000000000000 '
b110 $
b1111011 !
b1111011 (
b110111101111 )
b11001 %
b110111101011 "
b110111101011 #
#70
b1000 &
b100000000000000000000 '
b1010 $
b1111011 !
b1111011 (
b110111101111 )
b10101 %
b110111100111 "
b110111100111 #
#80
b100000 &
b10000000000000000000000000 '
b101 $
b1111011 !
b1111011 (
b110111101111 )
b11010 %
b110111001111 "
b110111001111 #
#90
b1000000 &
b10000000000000000000000 '
b1000 $
b1111011 !
b1111011 (
b110111101111 )
b10111 %
b110110101111 "
b110110101111 #
#100
b10000000 &
b10000000000000000 '
b1110 $
b1111011 !
b1111011 (
b110111101111 )
b10001 %
b110101101111 "
b110101101111 #
#110
b100000000 &
b10000 '
b11010 $
b1111011 !
b1111011 (
b110111101111 )
b101 %
b110011101111 "
b110011101111 #
#120
b10000000000 &
b10000000000000000000 '
b1011 $
b1111011 !
b1111011 (
b110111101111 )
b10100 %
b100111101111 "
b100111101111 #
#130
b100000000000 &
b10000000000 '
b10100 $
b1111011 !
b1111011 (
b110111101111 )
b1011 %
b10111101111 "
b10111101111 #
